README
cloudflu-clean
cloudflu-cluster-info
cloudflu-cluster-ls
cloudflu-cluster-rm
cloudflu-cluster-start
cloudflu-config
cloudflu-credentials-deploy
cloudflu-deploy
cloudflu-download
cloudflu-files-clean
cloudflu-foam2vtk
cloudflu-foam2vtk-after
cloudflu-foam2vtk-before
cloudflu-instance-extract
cloudflu-ls
cloudflu-nfs-config
cloudflu-openmpi-config
cloudflu-reservation-config
cloudflu-reservation-ls
cloudflu-reservation-run
cloudflu-rm
cloudflu-servers-clean
cloudflu-solver-process
cloudflu-solver-start
cloudflu-ssh
cloudflu-study-book
cloudflu-study-rm
cloudflu-study-seal
cloudflu-study-upload
cloudflu-timestamps-hook
cloudflu-timestamps-upload
cloudflu-upload-resume
cloudflu-upload-start
ez_setup.py
setup.py
cloudflu/__init__.py
cloudflu/config.py
cloudflu/pickup.py
cloudflu/preferences.py
cloudflu.egg-info/PKG-INFO
cloudflu.egg-info/SOURCES.txt
cloudflu.egg-info/dependency_links.txt
cloudflu.egg-info/requires.txt
cloudflu.egg-info/top_level.txt
cloudflu.egg-info/zip-safe
cloudflu/amazon/__init__.py
cloudflu/amazon/options.py
cloudflu/amazon/s3.py
cloudflu/amazon/security_options.py
cloudflu/amazon/apps/__init__.py
cloudflu/amazon/apps/cluster_info.py
cloudflu/amazon/apps/credentials_deploy.py
cloudflu/amazon/apps/credentials_deploy_options.py
cloudflu/amazon/apps/data_seeding_options.py
cloudflu/amazon/apps/data_transfer_options.py
cloudflu/amazon/apps/data_upload.py
cloudflu/amazon/apps/data_upload_options.py
cloudflu/amazon/apps/download.py
cloudflu/amazon/apps/download_options.py
cloudflu/amazon/apps/files_clean.py
cloudflu/amazon/apps/instance_extract.py
cloudflu/amazon/apps/instance_extract_options.py
cloudflu/amazon/apps/ls.py
cloudflu/amazon/apps/ls_options.py
cloudflu/amazon/apps/nfs_config.py
cloudflu/amazon/apps/openmpi_config.py
cloudflu/amazon/apps/openmpi_config_options.py
cloudflu/amazon/apps/reservation_ls.py
cloudflu/amazon/apps/reservation_rm.py
cloudflu/amazon/apps/reservation_rm_options.py
cloudflu/amazon/apps/reservation_run.py
cloudflu/amazon/apps/rm.py
cloudflu/amazon/apps/rm_options.py
cloudflu/amazon/apps/servers_clean.py
cloudflu/amazon/apps/solver_process.py
cloudflu/amazon/apps/solver_process_options.py
