Metadata-Version: 1.0
Name: cloudflu
Version: 0.28
Summary: Delivers "Cloud Computing" commodities for OpenFOAM(R) users
Home-page: http://sourceforge.net/projects/cloudflu
Author: Alexey Petrov
Author-email: alexey.petrov.nnov@gmail.com
License: Apache License, Version 2.0
Platform: linux
Classifier: Development Status :: 5 - Production/Stable
Classifier: Environment :: Console
Classifier: Intended Audience :: Science/Research
Classifier: License :: OSI Approved :: Apache Software License
Classifier: Operating System :: POSIX
Classifier: Programming Language :: Python
Classifier: Topic :: Scientific/Engineering
Classifier: Topic :: Utilities
